transformationsMR/__init__.py
transformationsMR/cross_correlation.py
transformationsMR/transpose2d.py
transformationsMR/ts_window.py
transformationsmr-0.1.0.dist-info/METADATA
transformationsmr-0.1.0.dist-info/WHEEL
transformationsmr-0.1.0.dist-info/RECORD
