Metadata-Version: 2.1
Name: transformationsMR
Version: 0.1.0
Summary: Common data transformation library used for machine learning. Includes 2D matrix transpose, time series windowing and cross-correlation functions.
License: Turing College
Author: Martynas Remeika
Author-email: martynas.remeika.a@gmail.com
Requires-Python: >=3.12,<4.0
Classifier: License :: Other/Proprietary License
Classifier: Programming Language :: Python :: 3
Classifier: Programming Language :: Python :: 3.12
Requires-Dist: numpy (>=1.26.3,<2.0.0)
